LICENSE.md
MANIFEST.in
README.md
dynamic_extras_require.txt
dynamic_install_requires.txt
quicklib_incorporated.v2.5.zip
quicklib_setup_from_yml.py
epic/common/__init__.py
epic/common/__version__.py
epic/common/assertion.py
epic/common/flow.py
epic/common/general.py
epic/common/importguard.py
epic/common/inspection.py
epic/common/io.py
epic/common/iteration.py
epic/common/nesteddict.py
epic/common/pathgeneralizer.py
epic/common/queue.py
epic/common/time.py
epic/common/tests/__init__.py
epic/common/tests/test_assertion.py
epic/common/tests/test_flow.py
epic/common/tests/test_importguard.py
epic/common/tests/test_inspection.py
epic/common/tests/test_pathgeneralizer.py
epic_common.egg-info/PKG-INFO
epic_common.egg-info/SOURCES.txt
epic_common.egg-info/dependency_links.txt
epic_common.egg-info/requires.txt
epic_common.egg-info/top_level.txt